chandler_banner/__init__.py
chandler_banner/chandler.py
chandler_banner-1.0.dist-info/METADATA
chandler_banner-1.0.dist-info/WHEEL
chandler_banner-1.0.dist-info/entry_points.txt
chandler_banner-1.0.dist-info/top_level.txt
chandler_banner-1.0.dist-info/RECORD
