Metadata-Version: 2.2
Name: chandler-banner
Version: 1.0
Summary: 一个终端彩色 ASCII 文字chandler liu12138的 Python 包
Home-page: https://github.com/1433223123/chandler_banner
Author: chandler Liu
Author-email: vhbzhl1234@gmail.com
Classifier: Programming Language :: Python :: 3
Classifier: License :: OSI Approved :: MIT License
Classifier: Operating System :: OS Independent
Requires-Python: >=3.6
Requires-Dist: pyfiglet
Requires-Dist: termcolor
Requires-Dist: colorama
Dynamic: author
Dynamic: author-email
Dynamic: classifier
Dynamic: description-content-type
Dynamic: home-page
Dynamic: requires-dist
Dynamic: requires-python
Dynamic: summary
